hightouch/htevents/__init__.py
hightouch/htevents/client.py
hightouch/htevents/consumer.py
hightouch/htevents/oauth_manager.py
hightouch/htevents/request.py
hightouch/htevents/utils.py
hightouch/htevents/version.py
hightouch/htevents/test/__init__.py
hightouch/htevents/test/client.py
hightouch/htevents/test/constants.py
hightouch/htevents/test/consumer.py
hightouch/htevents/test/module.py
hightouch/htevents/test/oauth.py
hightouch/htevents/test/request.py
hightouch/htevents/test/utils.py
events_sdk_python-0.0.3.dist-info/LICENSE
events_sdk_python-0.0.3.dist-info/METADATA
events_sdk_python-0.0.3.dist-info/WHEEL
events_sdk_python-0.0.3.dist-info/top_level.txt
events_sdk_python-0.0.3.dist-info/RECORD
