Metadata-Version: 2.1
Name: events-sdk-python
Version: 0.0.3
Summary: Events SDK Python for Hightouch event collection.
Author-email: Hightouch <engineering@hightouch.com>
License: MIT License
Project-URL: Homepage, https://github.com/ht-sdks/events-sdk-python
Classifier: Development Status :: 5 - Production/Stable
Classifier: Intended Audience :: Developers
Classifier: License :: OSI Approved :: MIT License
Classifier: Operating System :: OS Independent
Classifier: Programming Language :: Python
Classifier: Programming Language :: Python :: 3.6
Classifier: Programming Language :: Python :: 3.7
Classifier: Programming Language :: Python :: 3.8
Classifier: Programming Language :: Python :: 3.9
Classifier: Programming Language :: Python :: 3.10
Classifier: Programming Language :: Python :: 3.11
Requires-Python: >=3.6
License-File: LICENSE
Requires-Dist: requests ~=2.7
Requires-Dist: backoff ~=2.1
Requires-Dist: python-dateutil ~=2.2
Requires-Dist: PyJWT <3.0,>=2.0
Requires-Dist: pyjwt[crypto]
Provides-Extra: dev
Requires-Dist: mock ==2.0.0 ; extra == 'dev'
Requires-Dist: ruff ==0.1.4 ; extra == 'dev'
